README.md
setup.py
src/facile_gitlab_trigger.egg-info/PKG-INFO
src/facile_gitlab_trigger.egg-info/SOURCES.txt
src/facile_gitlab_trigger.egg-info/dependency_links.txt
src/facile_gitlab_trigger.egg-info/entry_points.txt
src/facile_gitlab_trigger.egg-info/requires.txt
src/facile_gitlab_trigger.egg-info/top_level.txt
src/facile_trigger_helper/__init__.py
src/facile_trigger_helper/facile_trigger_helper.py