Metadata-Version: 2.1
Name: facile-gitlab-trigger
Version: 0.0.24
Summary: testing 
Home-page: https://www.facile.it
Author: Fabio Lima
Author-email: f46io@icloud.com
License: UNKNOWN
Platform: any
